micropython_microbit_stubs_ja-0.0.1b2.dist-info/licenses/LICENSE.md
stdlib/abc.pyi
stdlib/antigravity.pyi
stdlib/array.pyi
stdlib/audio.pyi
stdlib/builtins.pyi
stdlib/errno.pyi
stdlib/gc.pyi
stdlib/log.pyi
stdlib/love.pyi
stdlib/machine.pyi
stdlib/math.pyi
stdlib/micropython.pyi
stdlib/music.pyi
stdlib/neopixel.pyi
stdlib/os.pyi
stdlib/power.pyi
stdlib/radio.pyi
stdlib/random.pyi
stdlib/speech.pyi
stdlib/struct.pyi
stdlib/sys.pyi
stdlib/this.pyi
stdlib/time.pyi
stdlib/types.pyi
stdlib/typing.pyi
stdlib/typing_extensions.pyi
stdlib/uarray.pyi
stdlib/ucollections.pyi
stdlib/uerrno.pyi
stdlib/urandom.pyi
stdlib/ustruct.pyi
stdlib/usys.pyi
stdlib/utime.pyi
stdlib/_typeshed/__init__.pyi
stdlib/collections/__init__.pyi
stdlib/microbit/__init__.pyi
stdlib/microbit/accelerometer.pyi
stdlib/microbit/audio.pyi
stdlib/microbit/compass.pyi
stdlib/microbit/display.pyi
stdlib/microbit/i2c.pyi
stdlib/microbit/microphone.pyi
stdlib/microbit/speaker.pyi
stdlib/microbit/spi.pyi
stdlib/microbit/uart.pyi
micropython_microbit_stubs_ja-0.0.1b2.dist-info/METADATA
micropython_microbit_stubs_ja-0.0.1b2.dist-info/WHEEL
micropython_microbit_stubs_ja-0.0.1b2.dist-info/top_level.txt
micropython_microbit_stubs_ja-0.0.1b2.dist-info/RECORD
